versionflow.py
versionflow-0.4.0.dist-info/METADATA
versionflow-0.4.0.dist-info/WHEEL
versionflow-0.4.0.dist-info/entry_points.txt
versionflow-0.4.0.dist-info/top_level.txt
versionflow-0.4.0.dist-info/RECORD
