Metadata-Version: 2.1
Name: versionflow
Version: 0.4.0
Summary: Automatic Semantic Versioning with Git Flow.
Home-page: https://github.com/Whatang/versionflow
Author: Mike Thomas
Author-email: versionflow@whatang.org
License: GPLv3
Keywords: versioning
Platform: UNKNOWN
Requires-Dist: click (==7.0)
Requires-Dist: setuptools-scm (==3.2.0)
Requires-Dist: attrs (==18.2.0)
Requires-Dist: bump2version (==0.5.10)
Requires-Dist: gitpython (==2.1.11)
Requires-Dist: nu-gitflow (==1.0.2)
Requires-Dist: configparser
Requires-Dist: six (==1.12.0)
